{
  "topic": "Numpy",
  "description": "Master high-performance numerical computing in Python.",
  "chapters": [
    {
      "id": "array-revolution",
      "title": "The Array Revolution",
      "description": "Discover why NumPy arrays are the heartbeat of modern AI and Data Science.",
      "file": "01-revolution.md",
      "order": 1
    },
    {
      "id": "anatomy-array",
      "title": "Anatomy of an Array",
      "description": "Learn to build and visualize 1D, 2D, and 3D data structures from scratch.",
      "file": "02-anatomy.md",
      "order": 2
    },
    {
      "id": "slicing-surgeon",
      "title": "The Slicing Surgeon",
      "description": "Extract exactly the data you need with surgical precision using indexing and slicing.",
      "file": "03-slicing.md",
      "order": 3
    },
    {
      "id": "shape-shifter",
      "title": "Shape Shifter",
      "description": "Master dimensions: Reshape, Flatten, and Transpose arrays to fit any model.",
      "file": "04-shape.md",
      "order": 4
    },
    {
      "id": "math-at-scale",
      "title": "Mathematics at Scale",
      "description": "Unlock the power of Broadcasting to perform math on millions of numbers instantly.",
      "file": "05-math.md",
      "order": 5
    },
    {
      "id": "statistical-insights",
      "title": "Statistical Insights",
      "description": "Derive meaning from chaos: Mean, Median, Deviation, and Percentiles.",
      "file": "06-stats.md",
      "order": 6
    },
    {
      "id": "linear-algebra",
      "title": "Linear Algebra Magic",
      "description": "The engine of Machine Learning: Dot products and Matrix multiplication simplified.",
      "file": "07-linalg.md",
      "order": 7
    },
    {
      "id": "randomness",
      "title": "Randomness & Probability",
      "description": "Simulate reality by generating synthetic data and probability distributions.",
      "file": "08-random.md",
      "order": 8
    },
    {
      "id": "file-mastery",
      "title": "File I/O Mastery",
      "description": "Save your work: Efficiently load and store massive datasets.",
      "file": "09-files.md",
      "order": 9
    },
    {
      "id": "capstone",
      "title": "Capstone: Finance Analysis",
      "description": "Apply everything you've learned to analyze a real-world stock market dataset.",
      "file": "10-capstone.md",
      "order": 10
    }
  ]
}